LICENSE
MANIFEST.in
README.md
setup.py
django_msgpackfield.egg-info/PKG-INFO
django_msgpackfield.egg-info/SOURCES.txt
django_msgpackfield.egg-info/dependency_links.txt
django_msgpackfield.egg-info/requires.txt
django_msgpackfield.egg-info/top_level.txt
msgpackfield/__init__.py
msgpackfield/msgpackfield.py