Metadata-Version: 2.1
Name: django-msgpackfield
Version: 0.15
Summary: UNKNOWN
Home-page: https://github.com/vakorol/django-msgpackfield
Author: Vasili Korol
Author-email: vakorol2000@gmail.com
License: MIT License
Platform: UNKNOWN
Classifier: Framework :: Django
Classifier: Framework :: Django :: 2.0
Classifier: Environment :: Web Environment
Classifier: Intended Audience :: Developers
Classifier: Operating System :: OS Independent
Classifier: Programming Language :: Python
Classifier: Programming Language :: Python :: 3
Classifier: Programming Language :: Python :: 3.4
Classifier: License :: OSI Approved :: MIT License
Classifier: Topic :: Utilities
Classifier: Topic :: Software Development :: Libraries :: Python Modules
Classifier: Development Status :: 4 - Beta
